[
  {
    "_id": "66f32c9f5f0a4c1a8e2a9b11",
    "LCid": "LC-1",
    "availableDate": "today",
    "availableShift": "morning",
    "createdById": "66f32ca05f0a4c1a8e2a9b44",
    "items": [
      {
        "_id": "66f32ca15f0a4c1a8e2a9b77",
        "itemId": "db63c0177cfae45a8385313a",
        "displayName": "Apple Fuji",
        "imageUrl": "https://upload.wikimedia.org/wikipedia/commons/6/67/Apfel-Fuji.jpg",
        "category": "fruit",
        "pricePerUnit": 3.0,
        "originalCommittedQuantityKg": 70,
        "currentAvailableQuantityKg": 70,
        "farmerOrderId": "66f32ca25f0a4c1a8e2a9baa",
        "farmerID": "66f32ca35f0a4c1a8e2a9bdd",
        "farmerName": "Levy Cohen",
        "farmName": "Galilee Orchards",
        "status": "active"
      }
    ]
  },
  {
    "_id": "66f32cab5f0a4c1a8e2a9d42",
    "LCid": "LC-1",
    "availableDate": "today",
    "availableShift": "afternoon",
    "createdById": "66f32cac5f0a4c1a8e2a9d75",
    "items": [
      {
        "_id": "66f32cad5f0a4c1a8e2a9da8",
        "itemId": "6873f67b8027abff0fdb32f3",
        "displayName": "Banana Cavendish",
        "imageUrl": "https://npr.brightspotcdn.com/dims4/default/654b07d/930x720/resize/880x681!/quality/90/?url=http://npr-brightspot.s3.amazonaws.com/legacy/sites/upr/files/201903/Bananas.jpg",
        "category": "fruit",
        "pricePerUnit": 3.6,
        "originalCommittedQuantityKg": 80,
        "currentAvailableQuantityKg": 74,
        "farmerOrderId": "66f32cae5f0a4c1a8e2a9ddb",
        "farmerID": "66f32caf5f0a4c1a8e2a9e0e",
        "farmerName": "Maya Klein",
        "farmName": "Kineret Farms",
        "status": "active"
      }
    ]
  },
  {
    "_id": "66f32cb95f0a4c1a8e2a9f99",
    "LCid": "LC-1",
    "availableDate": "today",
    "availableShift": "evening",
    "createdById": "66f32cb85f0a4c1a8e2a9f88",
    "items": [
      {
        "_id": "66f32cba5f0a4c1a8e2a9faa",
        "itemId": "fa56428339a4f47db7d15600",
        "displayName": "Cucumber Persian",
        "imageUrl": "https://d3awvtnmmsvyot.cloudfront.net/api/file/xEDVluyRB0wOXtvkCZ6w/convert?fit=max&w=570&cache=true",
        "category": "vegetable",
        "pricePerUnit": 4.2,
        "originalCommittedQuantityKg": 55,
        "currentAvailableQuantityKg": 51,
        "farmerOrderId": "66f32cb15f0a4c1a8e2a9e74",
        "farmerID": "66f32cb25f0a4c1a8e2a9ea7",
        "farmerName": "Tomer Azulay",
        "farmName": "Negev Greens",
        "status": "active"
      }
    ]
  },
  {
    "_id": "66f32cc05f0a4c1a8e2aa000",
    "LCid": "LC-1",
    "availableDate": "today",
    "availableShift": "night",
    "createdById": "66f32cbf5f0a4c1a8e2a9fff",
    "items": [
      {
        "_id": "66f32cc15f0a4c1a8e2aa011",
        "itemId": "30eb71d9a20cb517be34112f",
        "displayName": "Strawberry Albion",
        "imageUrl": "https://www.gurneys.com/cdn/shop/files/02165A.webp?v=1729086167",
        "category": "fruit",
        "pricePerUnit": 24.0,
        "originalCommittedQuantityKg": 50,
        "currentAvailableQuantityKg": 45,
        "farmerOrderId": "66f32cb45f0a4c1a8e2a9f0d",
        "farmerID": "66f32cb55f0a4c1a8e2a9f40",
        "farmerName": "Nurit Bar-On",
        "farmName": "Sharon Fields",
        "status": "active"
      }
    ]
  }
]
